{"key":"a556c5305ee15c3f-01|Num|13","bibleId":"a556c5305ee15c3f-01","bookAbbr":"Num","chapter":13,"textRevision":"api-bible-csb-2024","parserRevision":"v10","verses":[{"verseId":"a556c5305ee15c3f-01:Num:13:1","bibleId":"a556c5305ee15c3f-01","bookAbbr":"Num","bookOrder":3,"chapter":13,"verse":1,"text":"The Lord spoke to Moses:","textRevision":"api-bible-csb-2024"},{"verseId":"a556c5305ee15c3f-01:Num:13:2","bibleId":"a556c5305ee15c3f-01","bookAbbr":"Num","bookOrder":3,"chapter":13,"verse":2,"text":"“Send men to scout out the land of Canaan I am giving to the Israelites. Send one man who is a leader among them from each of their ancestral tribes.”","textRevision":"api-bible-csb-2024"},{"verseId":"a556c5305ee15c3f-01:Num:13:3","bibleId":"a556c5305ee15c3f-01","bookAbbr":"Num","bookOrder":3,"chapter":13,"verse":3,"text":"Moses sent them from the Wilderness of Paran at the Lord’s command. All the men were leaders in Israel.","textRevision":"api-bible-csb-2024"},{"verseId":"a556c5305ee15c3f-01:Num:13:4","bibleId":"a556c5305ee15c3f-01","bookAbbr":"Num","bookOrder":3,"chapter":13,"verse":4,"text":"These were their names:","textRevision":"api-bible-csb-2024"},{"verseId":"a556c5305ee15c3f-01:Num:13:5","bibleId":"a556c5305ee15c3f-01","bookAbbr":"Num","bookOrder":3,"chapter":13,"verse":5,"text":"Shaphat son of Hori from the tribe of Simeon;","textRevision":"api-bible-csb-2024"},{"verseId":"a556c5305ee15c3f-01:Num:13:6","bibleId":"a556c5305ee15c3f-01","bookAbbr":"Num","bookOrder":3,"chapter":13,"verse":6,"text":"Caleb son of Jephunneh from the tribe of Judah;","textRevision":"api-bible-csb-2024"},{"verseId":"a556c5305ee15c3f-01:Num:13:7","bibleId":"a556c5305ee15c3f-01","bookAbbr":"Num","bookOrder":3,"chapter":13,"verse":7,"text":"Igal son of Joseph from the tribe of Issachar;","textRevision":"api-bible-csb-2024"},{"verseId":"a556c5305ee15c3f-01:Num:13:8","bibleId":"a556c5305ee15c3f-01","bookAbbr":"Num","bookOrder":3,"chapter":13,"verse":8,"text":"Hoshea son of Nun from the tribe of Ephraim;","textRevision":"api-bible-csb-2024"},{"verseId":"a556c5305ee15c3f-01:Num:13:9","bibleId":"a556c5305ee15c3f-01","bookAbbr":"Num","bookOrder":3,"chapter":13,"verse":9,"text":"Palti son of Raphu from the tribe of Benjamin;","textRevision":"api-bible-csb-2024"},{"verseId":"a556c5305ee15c3f-01:Num:13:10","bibleId":"a556c5305ee15c3f-01","bookAbbr":"Num","bookOrder":3,"chapter":13,"verse":10,"text":"Gaddiel son of Sodi from the tribe of Zebulun;","textRevision":"api-bible-csb-2024"},{"verseId":"a556c5305ee15c3f-01:Num:13:11","bibleId":"a556c5305ee15c3f-01","bookAbbr":"Num","bookOrder":3,"chapter":13,"verse":11,"text":"Gaddi son of Susi from the tribe of Manasseh (from the tribe of Joseph);","textRevision":"api-bible-csb-2024"},{"verseId":"a556c5305ee15c3f-01:Num:13:12","bibleId":"a556c5305ee15c3f-01","bookAbbr":"Num","bookOrder":3,"chapter":13,"verse":12,"text":"Ammiel son of Gemalli from the tribe of Dan;","textRevision":"api-bible-csb-2024"},{"verseId":"a556c5305ee15c3f-01:Num:13:13","bibleId":"a556c5305ee15c3f-01","bookAbbr":"Num","bookOrder":3,"chapter":13,"verse":13,"text":"Sethur son of Michael from the tribe of Asher;","textRevision":"api-bible-csb-2024"},{"verseId":"a556c5305ee15c3f-01:Num:13:14","bibleId":"a556c5305ee15c3f-01","bookAbbr":"Num","bookOrder":3,"chapter":13,"verse":14,"text":"Nahbi son of Vophsi from the tribe of Naphtali;","textRevision":"api-bible-csb-2024"},{"verseId":"a556c5305ee15c3f-01:Num:13:15","bibleId":"a556c5305ee15c3f-01","bookAbbr":"Num","bookOrder":3,"chapter":13,"verse":15,"text":"Geuel son of Machi from the tribe of Gad.","textRevision":"api-bible-csb-2024"},{"verseId":"a556c5305ee15c3f-01:Num:13:16","bibleId":"a556c5305ee15c3f-01","bookAbbr":"Num","bookOrder":3,"chapter":13,"verse":16,"text":"These were the names of the men Moses sent to scout out the land, and Moses renamed Hoshea son of Nun, Joshua.","textRevision":"api-bible-csb-2024"},{"verseId":"a556c5305ee15c3f-01:Num:13:17","bibleId":"a556c5305ee15c3f-01","bookAbbr":"Num","bookOrder":3,"chapter":13,"verse":17,"text":"When Moses sent them to scout out the land of Canaan, he told them, “Go up this way to the Negev, then go up into the hill country.","textRevision":"api-bible-csb-2024"},{"verseId":"a556c5305ee15c3f-01:Num:13:18","bibleId":"a556c5305ee15c3f-01","bookAbbr":"Num","bookOrder":3,"chapter":13,"verse":18,"text":"See what the land is like, and whether the people who live there are strong or weak, few or many.","textRevision":"api-bible-csb-2024"},{"verseId":"a556c5305ee15c3f-01:Num:13:19","bibleId":"a556c5305ee15c3f-01","bookAbbr":"Num","bookOrder":3,"chapter":13,"verse":19,"text":"Is the land they live in good or bad? Are the cities they live in encampments or fortifications?","textRevision":"api-bible-csb-2024"},{"verseId":"a556c5305ee15c3f-01:Num:13:20","bibleId":"a556c5305ee15c3f-01","bookAbbr":"Num","bookOrder":3,"chapter":13,"verse":20,"text":"Is the land fertile or unproductive? Are there trees in it or not? Be courageous. Bring back some fruit from the land.” It was the season for the first ripe grapes.","textRevision":"api-bible-csb-2024"},{"verseId":"a556c5305ee15c3f-01:Num:13:21","bibleId":"a556c5305ee15c3f-01","bookAbbr":"Num","bookOrder":3,"chapter":13,"verse":21,"text":"So they went up and scouted out the land from the Wilderness of Zin as far as Rehob near the entrance to Hamath.","textRevision":"api-bible-csb-2024"},{"verseId":"a556c5305ee15c3f-01:Num:13:22","bibleId":"a556c5305ee15c3f-01","bookAbbr":"Num","bookOrder":3,"chapter":13,"verse":22,"text":"They went up through the Negev and came to Hebron, where Ahiman, Sheshai, and Talmai, the descendants of Anak, were living. Hebron was built seven years before Zoan in Egypt.","textRevision":"api-bible-csb-2024"},{"verseId":"a556c5305ee15c3f-01:Num:13:23","bibleId":"a556c5305ee15c3f-01","bookAbbr":"Num","bookOrder":3,"chapter":13,"verse":23,"text":"When they came to Eshcol Valley, they cut down a branch with a single cluster of grapes, which was carried on a pole by two men. They also took some pomegranates and figs.","textRevision":"api-bible-csb-2024"},{"verseId":"a556c5305ee15c3f-01:Num:13:24","bibleId":"a556c5305ee15c3f-01","bookAbbr":"Num","bookOrder":3,"chapter":13,"verse":24,"text":"That place was called Eshcol Valley because of the cluster of grapes the Israelites cut there.","textRevision":"api-bible-csb-2024"},{"verseId":"a556c5305ee15c3f-01:Num:13:25","bibleId":"a556c5305ee15c3f-01","bookAbbr":"Num","bookOrder":3,"chapter":13,"verse":25,"text":"At the end of forty days they returned from scouting out the land.","textRevision":"api-bible-csb-2024"},{"verseId":"a556c5305ee15c3f-01:Num:13:26","bibleId":"a556c5305ee15c3f-01","bookAbbr":"Num","bookOrder":3,"chapter":13,"verse":26,"text":"The men went back to Moses, Aaron, and the entire Israelite community in the Wilderness of Paran at Kadesh. They brought back a report for them and the whole community, and they showed them the fruit of the land.","textRevision":"api-bible-csb-2024"},{"verseId":"a556c5305ee15c3f-01:Num:13:27","bibleId":"a556c5305ee15c3f-01","bookAbbr":"Num","bookOrder":3,"chapter":13,"verse":27,"text":"They reported to Moses, “We went into the land where you sent us. Indeed it is flowing with milk and honey, and here is some of its fruit.","textRevision":"api-bible-csb-2024"},{"verseId":"a556c5305ee15c3f-01:Num:13:28","bibleId":"a556c5305ee15c3f-01","bookAbbr":"Num","bookOrder":3,"chapter":13,"verse":28,"text":"However, the people living in the land are strong, and the cities are large and fortified. We also saw the descendants of Anak there.","textRevision":"api-bible-csb-2024"},{"verseId":"a556c5305ee15c3f-01:Num:13:29","bibleId":"a556c5305ee15c3f-01","bookAbbr":"Num","bookOrder":3,"chapter":13,"verse":29,"text":"The Amalekites are living in the land of the Negev; the Hethites, Jebusites, and Amorites live in the hill country; and the Canaanites live by the sea and along the Jordan.”","textRevision":"api-bible-csb-2024"},{"verseId":"a556c5305ee15c3f-01:Num:13:30","bibleId":"a556c5305ee15c3f-01","bookAbbr":"Num","bookOrder":3,"chapter":13,"verse":30,"text":"Then Caleb quieted the people in the presence of Moses and said, “Let’s go up now and take possession of the land because we can certainly conquer it!”","textRevision":"api-bible-csb-2024"},{"verseId":"a556c5305ee15c3f-01:Num:13:31","bibleId":"a556c5305ee15c3f-01","bookAbbr":"Num","bookOrder":3,"chapter":13,"verse":31,"text":"But the men who had gone up with him responded, “We can’t attack the people because they are stronger than we are!”","textRevision":"api-bible-csb-2024"},{"verseId":"a556c5305ee15c3f-01:Num:13:32","bibleId":"a556c5305ee15c3f-01","bookAbbr":"Num","bookOrder":3,"chapter":13,"verse":32,"text":"So they gave a negative report to the Israelites about the land they had scouted: “The land we passed through to explore is one that devours its inhabitants, and all the people we saw in it are men of great size.","textRevision":"api-bible-csb-2024"},{"verseId":"a556c5305ee15c3f-01:Num:13:33","bibleId":"a556c5305ee15c3f-01","bookAbbr":"Num","bookOrder":3,"chapter":13,"verse":33,"text":"We even saw the Nephilim there —the descendants of Anak come from the Nephilim! To ourselves we seemed like grasshoppers, and we must have seemed the same to them.”","textRevision":"api-bible-csb-2024"}],"layout":{"bibleId":"a556c5305ee15c3f-01","bookAbbr":"Num","chapter":13,"paragraphStarts":[1,5,6,7,8,9,10,11,12,13,14,15,16,17,21,26,30,31],"headings":[{"beforeVerse":1,"text":"Scouting Out Canaan"},{"beforeVerse":26,"text":"Report about Canaan"}],"poetryBlocks":[],"studyByVerse":[{"verseId":"a556c5305ee15c3f-01:Num:13:1","parts":[{"kind":"text","text":"The "},{"kind":"text","text":"Lord","style":"divine"},{"kind":"text","text":" spoke to Moses: "}],"crossRefs":[],"footnotes":[]},{"verseId":"a556c5305ee15c3f-01:Num:13:2","parts":[{"kind":"text","text":"“Send men to scout out the land of Canaan "},{"kind":"crossref","label":"Dt 1:22","book":"Deu","chapter":1,"verse":22,"letter":"a"},{"kind":"text","text":" I am giving to the Israelites. Send one man who is a leader among them from each of their ancestral tribes.” "}],"crossRefs":[{"label":"Dt 1:22","book":"Deu","chapter":1,"verse":22}],"footnotes":[]},{"verseId":"a556c5305ee15c3f-01:Num:13:3","parts":[{"kind":"text","text":"Moses sent them from the Wilderness of Paran at the "},{"kind":"text","text":"Lord","style":"divine"},{"kind":"text","text":"’s command. All the men were leaders in Israel. "},{"kind":"crossref","label":"Ex 18:25–26","book":"Exo","chapter":18,"verse":25,"letter":"a"},{"kind":"crossref","label":"Dt 1:13","book":"Deu","chapter":1,"verse":13,"letter":"b"},{"kind":"text","text":" "}],"crossRefs":[{"label":"Ex 18:25–26","book":"Exo","chapter":18,"verse":25},{"label":"Dt 1:13","book":"Deu","chapter":1,"verse":13}],"footnotes":[]},{"verseId":"a556c5305ee15c3f-01:Num:13:4","parts":[{"kind":"text","text":"These were their names:"}],"crossRefs":[],"footnotes":[]},{"verseId":"a556c5305ee15c3f-01:Num:13:5","parts":[{"kind":"text","text":"Shaphat son of Hori from the tribe of Simeon;"}],"crossRefs":[],"footnotes":[]},{"verseId":"a556c5305ee15c3f-01:Num:13:6","parts":[{"kind":"text","text":"Caleb "},{"kind":"crossref","label":"Nm 14:6","book":"Num","chapter":14,"verse":6,"letter":"a"},{"kind":"crossref","label":"Nm 14:24","book":"Num","chapter":14,"verse":24,"letter":"b"},{"kind":"crossref","label":"Nm 14:30","book":"Num","chapter":14,"verse":30,"letter":"c"},{"kind":"crossref","label":"Nm 14:38","book":"Num","chapter":14,"verse":38,"letter":"d"},{"kind":"crossref","label":"Nm 26:65","book":"Num","chapter":26,"verse":65,"letter":"e"},{"kind":"text","text":" son of Jephunneh from the tribe of Judah;"}],"crossRefs":[{"label":"Nm 14:6","book":"Num","chapter":14,"verse":6},{"label":"Nm 14:24","book":"Num","chapter":14,"verse":24},{"label":"Nm 14:30","book":"Num","chapter":14,"verse":30},{"label":"Nm 14:38","book":"Num","chapter":14,"verse":38},{"label":"Nm 26:65","book":"Num","chapter":26,"verse":65}],"footnotes":[]},{"verseId":"a556c5305ee15c3f-01:Num:13:7","parts":[{"kind":"text","text":"Igal son of Joseph from the tribe of Issachar;"}],"crossRefs":[],"footnotes":[]},{"verseId":"a556c5305ee15c3f-01:Num:13:8","parts":[{"kind":"text","text":"Hoshea son of Nun "},{"kind":"crossref","label":"Ex 33:11","book":"Exo","chapter":33,"verse":11,"letter":"a"},{"kind":"crossref","label":"Nm 14:30","book":"Num","chapter":14,"verse":30,"letter":"b"},{"kind":"crossref","label":"Nm 14:38","book":"Num","chapter":14,"verse":38,"letter":"c"},{"kind":"crossref","label":"Nm 27:18–23","book":"Num","chapter":27,"verse":18,"letter":"d"},{"kind":"text","text":" from the tribe of Ephraim;"}],"crossRefs":[{"label":"Ex 33:11","book":"Exo","chapter":33,"verse":11},{"label":"Nm 14:30","book":"Num","chapter":14,"verse":30},{"label":"Nm 14:38","book":"Num","chapter":14,"verse":38},{"label":"Nm 27:18–23","book":"Num","chapter":27,"verse":18}],"footnotes":[]},{"verseId":"a556c5305ee15c3f-01:Num:13:9","parts":[{"kind":"text","text":"Palti son of Raphu from the tribe of Benjamin;"}],"crossRefs":[],"footnotes":[]},{"verseId":"a556c5305ee15c3f-01:Num:13:10","parts":[{"kind":"text","text":"Gaddiel son of Sodi from the tribe of Zebulun;"}],"crossRefs":[],"footnotes":[]},{"verseId":"a556c5305ee15c3f-01:Num:13:11","parts":[{"kind":"text","text":"Gaddi son of Susi from the tribe of Manasseh (from the tribe of Joseph);"}],"crossRefs":[],"footnotes":[]},{"verseId":"a556c5305ee15c3f-01:Num:13:12","parts":[{"kind":"text","text":"Ammiel son of Gemalli from the tribe of Dan;"}],"crossRefs":[],"footnotes":[]},{"verseId":"a556c5305ee15c3f-01:Num:13:13","parts":[{"kind":"text","text":"Sethur son of Michael from the tribe of Asher;"}],"crossRefs":[],"footnotes":[]},{"verseId":"a556c5305ee15c3f-01:Num:13:14","parts":[{"kind":"text","text":"Nahbi son of Vophsi from the tribe of Naphtali;"}],"crossRefs":[],"footnotes":[]},{"verseId":"a556c5305ee15c3f-01:Num:13:15","parts":[{"kind":"text","text":"Geuel son of Machi from the tribe of Gad."}],"crossRefs":[],"footnotes":[]},{"verseId":"a556c5305ee15c3f-01:Num:13:16","parts":[{"kind":"text","text":"These were the names of the men Moses sent to scout out the land, and Moses renamed Hoshea son of Nun, Joshua."}],"crossRefs":[],"footnotes":[]},{"verseId":"a556c5305ee15c3f-01:Num:13:17","parts":[{"kind":"text","text":"When Moses sent them to scout out the land of Canaan, he told them, “Go up this way to the Negev, then go up into the hill country. "}],"crossRefs":[],"footnotes":[]},{"verseId":"a556c5305ee15c3f-01:Num:13:18","parts":[{"kind":"text","text":"See what the land is like, and whether the people who live there are strong or weak, few or many. "}],"crossRefs":[],"footnotes":[]},{"verseId":"a556c5305ee15c3f-01:Num:13:19","parts":[{"kind":"text","text":"Is the land they live in good "},{"kind":"crossref","label":"Nm 14:7","book":"Num","chapter":14,"verse":7,"letter":"a"},{"kind":"crossref","label":"Dt 1:25","book":"Deu","chapter":1,"verse":25,"letter":"b"},{"kind":"text","text":" or bad? Are the cities they live in encampments or fortifications? "},{"kind":"crossref","label":"Dt 1:28","book":"Deu","chapter":1,"verse":28,"letter":"c"},{"kind":"crossref","label":"Dt 3:5","book":"Deu","chapter":3,"verse":5,"letter":"d"},{"kind":"crossref","label":"Dt 9:1","book":"Deu","chapter":9,"verse":1,"letter":"e"},{"kind":"crossref","label":"Jos 14:12","book":"Jos","chapter":14,"verse":12,"letter":"f"},{"kind":"text","text":" "}],"crossRefs":[{"label":"Nm 14:7","book":"Num","chapter":14,"verse":7},{"label":"Dt 1:25","book":"Deu","chapter":1,"verse":25},{"label":"Dt 1:28","book":"Deu","chapter":1,"verse":28},{"label":"Dt 3:5","book":"Deu","chapter":3,"verse":5},{"label":"Dt 9:1","book":"Deu","chapter":9,"verse":1},{"label":"Jos 14:12","book":"Jos","chapter":14,"verse":12}],"footnotes":[]},{"verseId":"a556c5305ee15c3f-01:Num:13:20","parts":[{"kind":"text","text":"Is the land fertile or unproductive? "},{"kind":"crossref","label":"Neh 9:25","book":"Neh","chapter":9,"verse":25,"letter":"a"},{"kind":"crossref","label":"Neh 9:35","book":"Neh","chapter":9,"verse":35,"letter":"b"},{"kind":"crossref","label":"Is 30:23","book":"Isa","chapter":30,"verse":23,"letter":"c"},{"kind":"crossref","label":"Ezk 34:14","book":"Ezk","chapter":34,"verse":14,"letter":"d"},{"kind":"crossref","label":"Ezk 34:20","book":"Ezk","chapter":34,"verse":20,"letter":"e"},{"kind":"text","text":" Are there trees in it or not? Be courageous. Bring back some fruit from the land.” It was the season for the first ripe grapes. "},{"kind":"crossref","label":"Nm 13:23","book":"Num","chapter":13,"verse":23,"letter":"f"}],"crossRefs":[{"label":"Neh 9:25","book":"Neh","chapter":9,"verse":25},{"label":"Neh 9:35","book":"Neh","chapter":9,"verse":35},{"label":"Is 30:23","book":"Isa","chapter":30,"verse":23},{"label":"Ezk 34:14","book":"Ezk","chapter":34,"verse":14},{"label":"Ezk 34:20","book":"Ezk","chapter":34,"verse":20},{"label":"Nm 13:23","book":"Num","chapter":13,"verse":23}],"footnotes":[]},{"verseId":"a556c5305ee15c3f-01:Num:13:21","parts":[{"kind":"text","text":"So they went up and scouted out the land from the Wilderness of Zin "},{"kind":"footnote","marker":1,"text":"Southern border of the promised land"},{"kind":"text","text":" as far as Rehob near the entrance to Hamath. "},{"kind":"footnote","marker":2,"text":"Or near Lebo-hamath"},{"kind":"text","text":" "}],"crossRefs":[],"footnotes":[{"marker":1,"text":"Southern border of the promised land"},{"marker":2,"text":"Or near Lebo-hamath"}]},{"verseId":"a556c5305ee15c3f-01:Num:13:22","parts":[{"kind":"text","text":"They went up through the Negev and came to Hebron, where Ahiman, Sheshai, and Talmai, the descendants of Anak, "},{"kind":"crossref","label":"Nm 13:28","book":"Num","chapter":13,"verse":28,"letter":"a"},{"kind":"crossref","label":"Nm 13:33","book":"Num","chapter":13,"verse":33,"letter":"b"},{"kind":"crossref","label":"Dt 1:28","book":"Deu","chapter":1,"verse":28,"letter":"c"},{"kind":"crossref","label":"Dt 2:10–11","book":"Deu","chapter":2,"verse":10,"letter":"d"},{"kind":"crossref","label":"Dt 2:21","book":"Deu","chapter":2,"verse":21,"letter":"e"},{"kind":"text","text":" were living. Hebron was built seven years before Zoan "},{"kind":"crossref","label":"Ps 78:12","book":"Psa","chapter":78,"verse":12,"letter":"f"},{"kind":"crossref","label":"Is 19:11","book":"Isa","chapter":19,"verse":11,"letter":"g"},{"kind":"crossref","label":"Is 30:4","book":"Isa","chapter":30,"verse":4,"letter":"h"},{"kind":"crossref","label":"Ezk 30:14","book":"Ezk","chapter":30,"verse":14,"letter":"i"},{"kind":"text","text":" in Egypt. "}],"crossRefs":[{"label":"Nm 13:28","book":"Num","chapter":13,"verse":28},{"label":"Nm 13:33","book":"Num","chapter":13,"verse":33},{"label":"Dt 1:28","book":"Deu","chapter":1,"verse":28},{"label":"Dt 2:10–11","book":"Deu","chapter":2,"verse":10},{"label":"Dt 2:21","book":"Deu","chapter":2,"verse":21},{"label":"Ps 78:12","book":"Psa","chapter":78,"verse":12},{"label":"Is 19:11","book":"Isa","chapter":19,"verse":11},{"label":"Is 30:4","book":"Isa","chapter":30,"verse":4},{"label":"Ezk 30:14","book":"Ezk","chapter":30,"verse":14}],"footnotes":[]},{"verseId":"a556c5305ee15c3f-01:Num:13:23","parts":[{"kind":"text","text":"When they came to Eshcol "},{"kind":"crossref","label":"Nm 32:9","book":"Num","chapter":32,"verse":9,"letter":"a"},{"kind":"crossref","label":"Dt 1:24","book":"Deu","chapter":1,"verse":24,"letter":"b"},{"kind":"text","text":" Valley, they cut down a branch with a single cluster of grapes, which was carried on a pole by two men. They also took some pomegranates and figs. "},{"kind":"crossref","label":"Nm 20:5","book":"Num","chapter":20,"verse":5,"letter":"c"},{"kind":"crossref","label":"Dt 8:8","book":"Deu","chapter":8,"verse":8,"letter":"d"},{"kind":"text","text":" "}],"crossRefs":[{"label":"Nm 32:9","book":"Num","chapter":32,"verse":9},{"label":"Dt 1:24","book":"Deu","chapter":1,"verse":24},{"label":"Nm 20:5","book":"Num","chapter":20,"verse":5},{"label":"Dt 8:8","book":"Deu","chapter":8,"verse":8}],"footnotes":[]},{"verseId":"a556c5305ee15c3f-01:Num:13:24","parts":[{"kind":"text","text":"That place was called Eshcol "},{"kind":"footnote","marker":3,"text":"= Cluster"},{"kind":"text","text":" Valley because of the cluster of grapes the Israelites cut there. "}],"crossRefs":[],"footnotes":[{"marker":3,"text":"= Cluster"}]},{"verseId":"a556c5305ee15c3f-01:Num:13:25","parts":[{"kind":"text","text":"At the end of forty days "},{"kind":"crossref","label":"Nm 14:33","book":"Num","chapter":14,"verse":33,"letter":"a"},{"kind":"crossref","label":"Nm 32:13","book":"Num","chapter":32,"verse":13,"letter":"b"},{"kind":"crossref","label":"Ps 95:10","book":"Psa","chapter":95,"verse":10,"letter":"c"},{"kind":"text","text":" they returned from scouting out the land."}],"crossRefs":[{"label":"Nm 14:33","book":"Num","chapter":14,"verse":33},{"label":"Nm 32:13","book":"Num","chapter":32,"verse":13},{"label":"Ps 95:10","book":"Psa","chapter":95,"verse":10}],"footnotes":[]},{"verseId":"a556c5305ee15c3f-01:Num:13:26","parts":[{"kind":"text","text":"The men went back to Moses, Aaron, and the entire Israelite community in the Wilderness of Paran at Kadesh. They brought back a report for them and the whole community, and they showed them the fruit of the land. "},{"kind":"crossref","label":"Nm 32:9","book":"Num","chapter":32,"verse":9,"letter":"a"},{"kind":"crossref","label":"Dt 1:24","book":"Deu","chapter":1,"verse":24,"letter":"b"},{"kind":"text","text":" "}],"crossRefs":[{"label":"Nm 32:9","book":"Num","chapter":32,"verse":9},{"label":"Dt 1:24","book":"Deu","chapter":1,"verse":24}],"footnotes":[]},{"verseId":"a556c5305ee15c3f-01:Num:13:27","parts":[{"kind":"text","text":"They reported to Moses, “We went into the land where you sent us. Indeed it is flowing with milk and honey, "},{"kind":"crossref","label":"Ex 3:8","book":"Exo","chapter":3,"verse":8,"letter":"a"},{"kind":"crossref","label":"Lv 20:24","book":"Lev","chapter":20,"verse":24,"letter":"b"},{"kind":"crossref","label":"Nm 14:8","book":"Num","chapter":14,"verse":8,"letter":"c"},{"kind":"crossref","label":"Nm 16:13–14","book":"Num","chapter":16,"verse":13,"letter":"d"},{"kind":"text","text":" and here is some of its fruit. "}],"crossRefs":[{"label":"Ex 3:8","book":"Exo","chapter":3,"verse":8},{"label":"Lv 20:24","book":"Lev","chapter":20,"verse":24},{"label":"Nm 14:8","book":"Num","chapter":14,"verse":8},{"label":"Nm 16:13–14","book":"Num","chapter":16,"verse":13}],"footnotes":[]},{"verseId":"a556c5305ee15c3f-01:Num:13:28","parts":[{"kind":"text","text":"However, the people living in the land are strong, and the cities are large and fortified. "},{"kind":"crossref","label":"Dt 1:28","book":"Deu","chapter":1,"verse":28,"letter":"a"},{"kind":"crossref","label":"Dt 3:5","book":"Deu","chapter":3,"verse":5,"letter":"b"},{"kind":"crossref","label":"Dt 9:1","book":"Deu","chapter":9,"verse":1,"letter":"c"},{"kind":"crossref","label":"Jos 14:12","book":"Jos","chapter":14,"verse":12,"letter":"d"},{"kind":"text","text":" We also saw the descendants of Anak "},{"kind":"crossref","label":"Nm 13:22","book":"Num","chapter":13,"verse":22,"letter":"e"},{"kind":"crossref","label":"Nm 13:33","book":"Num","chapter":13,"verse":33,"letter":"f"},{"kind":"crossref","label":"Dt 1:28","book":"Deu","chapter":1,"verse":28,"letter":"g"},{"kind":"crossref","label":"Dt 2:10–11","book":"Deu","chapter":2,"verse":10,"letter":"h"},{"kind":"crossref","label":"Dt 2:21","book":"Deu","chapter":2,"verse":21,"letter":"i"},{"kind":"text","text":" there. "}],"crossRefs":[{"label":"Dt 1:28","book":"Deu","chapter":1,"verse":28},{"label":"Dt 3:5","book":"Deu","chapter":3,"verse":5},{"label":"Dt 9:1","book":"Deu","chapter":9,"verse":1},{"label":"Jos 14:12","book":"Jos","chapter":14,"verse":12},{"label":"Nm 13:22","book":"Num","chapter":13,"verse":22},{"label":"Nm 13:33","book":"Num","chapter":13,"verse":33},{"label":"Dt 1:28","book":"Deu","chapter":1,"verse":28},{"label":"Dt 2:10–11","book":"Deu","chapter":2,"verse":10},{"label":"Dt 2:21","book":"Deu","chapter":2,"verse":21}],"footnotes":[]},{"verseId":"a556c5305ee15c3f-01:Num:13:29","parts":[{"kind":"text","text":"The Amalekites "},{"kind":"crossref","label":"Ex 17:8–16","book":"Exo","chapter":17,"verse":8,"letter":"a"},{"kind":"crossref","label":"Nm 14:25","book":"Num","chapter":14,"verse":25,"letter":"b"},{"kind":"crossref","label":"Nm 14:43","book":"Num","chapter":14,"verse":43,"letter":"c"},{"kind":"crossref","label":"Nm 14:45","book":"Num","chapter":14,"verse":45,"letter":"d"},{"kind":"crossref","label":"Dt 25:17","book":"Deu","chapter":25,"verse":17,"letter":"e"},{"kind":"text","text":" are living in the land of the Negev; the Hethites, Jebusites, and Amorites live in the hill country; and the Canaanites live by the sea and along the Jordan.”"}],"crossRefs":[{"label":"Ex 17:8–16","book":"Exo","chapter":17,"verse":8},{"label":"Nm 14:25","book":"Num","chapter":14,"verse":25},{"label":"Nm 14:43","book":"Num","chapter":14,"verse":43},{"label":"Nm 14:45","book":"Num","chapter":14,"verse":45},{"label":"Dt 25:17","book":"Deu","chapter":25,"verse":17}],"footnotes":[]},{"verseId":"a556c5305ee15c3f-01:Num:13:30","parts":[{"kind":"text","text":"Then Caleb "},{"kind":"crossref","label":"Nm 14:6","book":"Num","chapter":14,"verse":6,"letter":"a"},{"kind":"crossref","label":"Nm 14:24","book":"Num","chapter":14,"verse":24,"letter":"b"},{"kind":"crossref","label":"Nm 14:30","book":"Num","chapter":14,"verse":30,"letter":"c"},{"kind":"crossref","label":"Nm 14:38","book":"Num","chapter":14,"verse":38,"letter":"d"},{"kind":"crossref","label":"Nm 26:65","book":"Num","chapter":26,"verse":65,"letter":"e"},{"kind":"text","text":" quieted the people in the presence of Moses and said, “Let’s go up now and take possession of the land because we can certainly conquer it!”"}],"crossRefs":[{"label":"Nm 14:6","book":"Num","chapter":14,"verse":6},{"label":"Nm 14:24","book":"Num","chapter":14,"verse":24},{"label":"Nm 14:30","book":"Num","chapter":14,"verse":30},{"label":"Nm 14:38","book":"Num","chapter":14,"verse":38},{"label":"Nm 26:65","book":"Num","chapter":26,"verse":65}],"footnotes":[]},{"verseId":"a556c5305ee15c3f-01:Num:13:31","parts":[{"kind":"text","text":"But the men who had gone up with him responded, “We can’t attack the people because they are stronger than we are!” "}],"crossRefs":[],"footnotes":[]},{"verseId":"a556c5305ee15c3f-01:Num:13:32","parts":[{"kind":"text","text":"So they gave a negative report to the Israelites about the land they had scouted: “The land we passed through to explore is one that devours its inhabitants, and all the people we saw in it are men of great size. "}],"crossRefs":[],"footnotes":[]},{"verseId":"a556c5305ee15c3f-01:Num:13:33","parts":[{"kind":"text","text":"We even saw the Nephilim "},{"kind":"crossref","label":"Gn 6:4","book":"Gen","chapter":6,"verse":4,"letter":"a"},{"kind":"text","text":" there —the descendants of Anak come from the Nephilim! "},{"kind":"crossref","label":"Dt 2:10","book":"Deu","chapter":2,"verse":10,"letter":"b"},{"kind":"crossref","label":"Dt 2:20","book":"Deu","chapter":2,"verse":20,"letter":"c"},{"kind":"text","text":" To ourselves we seemed like grasshoppers, and we must have seemed the same to them.”"}],"crossRefs":[{"label":"Gn 6:4","book":"Gen","chapter":6,"verse":4},{"label":"Dt 2:10","book":"Deu","chapter":2,"verse":10},{"label":"Dt 2:20","book":"Deu","chapter":2,"verse":20}],"footnotes":[]}]},"cachedAt":1783099251581}