{"key":"a556c5305ee15c3f-01|Psa|138","bibleId":"a556c5305ee15c3f-01","bookAbbr":"Psa","chapter":138,"textRevision":"api-bible-csb-2024","parserRevision":"v10","verses":[{"verseId":"a556c5305ee15c3f-01:Psa:138:1","bibleId":"a556c5305ee15c3f-01","bookAbbr":"Psa","bookOrder":18,"chapter":138,"verse":1,"text":"I will give you thanks with all my heart;","textRevision":"api-bible-csb-2024"},{"verseId":"a556c5305ee15c3f-01:Psa:138:2","bibleId":"a556c5305ee15c3f-01","bookAbbr":"Psa","bookOrder":18,"chapter":138,"verse":2,"text":"I will bow down toward your holy temple","textRevision":"api-bible-csb-2024"},{"verseId":"a556c5305ee15c3f-01:Psa:138:3","bibleId":"a556c5305ee15c3f-01","bookAbbr":"Psa","bookOrder":18,"chapter":138,"verse":3,"text":"On the day I called, you answered me;","textRevision":"api-bible-csb-2024"},{"verseId":"a556c5305ee15c3f-01:Psa:138:4","bibleId":"a556c5305ee15c3f-01","bookAbbr":"Psa","bookOrder":18,"chapter":138,"verse":4,"text":"All the kings on earth will give you thanks, Lord,","textRevision":"api-bible-csb-2024"},{"verseId":"a556c5305ee15c3f-01:Psa:138:5","bibleId":"a556c5305ee15c3f-01","bookAbbr":"Psa","bookOrder":18,"chapter":138,"verse":5,"text":"They will sing of the Lord’s ways,","textRevision":"api-bible-csb-2024"},{"verseId":"a556c5305ee15c3f-01:Psa:138:6","bibleId":"a556c5305ee15c3f-01","bookAbbr":"Psa","bookOrder":18,"chapter":138,"verse":6,"text":"Though the Lord is exalted,","textRevision":"api-bible-csb-2024"},{"verseId":"a556c5305ee15c3f-01:Psa:138:7","bibleId":"a556c5305ee15c3f-01","bookAbbr":"Psa","bookOrder":18,"chapter":138,"verse":7,"text":"If I walk into the thick of danger,","textRevision":"api-bible-csb-2024"},{"verseId":"a556c5305ee15c3f-01:Psa:138:8","bibleId":"a556c5305ee15c3f-01","bookAbbr":"Psa","bookOrder":18,"chapter":138,"verse":8,"text":"The Lord will fulfill his purpose for me.","textRevision":"api-bible-csb-2024"}],"layout":{"bibleId":"a556c5305ee15c3f-01","bookAbbr":"Psa","chapter":138,"paragraphStarts":[1,2,3,4,5,6,7,8],"headings":[{"beforeVerse":1,"text":"Of David."}],"poetryBlocks":[{"beforeVerse":1,"level":1},{"beforeVerse":2,"level":1},{"beforeVerse":3,"level":1},{"beforeVerse":4,"level":1},{"beforeVerse":5,"level":1},{"beforeVerse":6,"level":1},{"beforeVerse":7,"level":1},{"beforeVerse":8,"level":1}],"studyByVerse":[{"verseId":"a556c5305ee15c3f-01:Psa:138:1","parts":[{"kind":"text","text":"I will give you thanks with all my heart; "},{"kind":"crossref","label":"Ps 111:1","book":"Psa","chapter":111,"verse":1,"letter":"a"}],"crossRefs":[{"label":"Ps 111:1","book":"Psa","chapter":111,"verse":1}],"footnotes":[]},{"verseId":"a556c5305ee15c3f-01:Psa:138:2","parts":[{"kind":"text","text":"I will bow down toward your holy temple"}],"crossRefs":[],"footnotes":[]},{"verseId":"a556c5305ee15c3f-01:Psa:138:3","parts":[{"kind":"text","text":"On the day I called, you answered me;"}],"crossRefs":[],"footnotes":[]},{"verseId":"a556c5305ee15c3f-01:Psa:138:4","parts":[{"kind":"text","text":"All the kings on earth will give you thanks, "},{"kind":"text","text":"Lord","style":"divine"},{"kind":"text","text":","}],"crossRefs":[],"footnotes":[]},{"verseId":"a556c5305ee15c3f-01:Psa:138:5","parts":[{"kind":"text","text":"They will sing of the "},{"kind":"text","text":"Lord","style":"divine"},{"kind":"text","text":"’s ways,"}],"crossRefs":[],"footnotes":[]},{"verseId":"a556c5305ee15c3f-01:Psa:138:6","parts":[{"kind":"text","text":"Though the "},{"kind":"text","text":"Lord","style":"divine"},{"kind":"text","text":" is exalted,"}],"crossRefs":[],"footnotes":[]},{"verseId":"a556c5305ee15c3f-01:Psa:138:7","parts":[{"kind":"text","text":"If I walk into the thick of danger,"}],"crossRefs":[],"footnotes":[]},{"verseId":"a556c5305ee15c3f-01:Psa:138:8","parts":[{"kind":"text","text":"The "},{"kind":"text","text":"Lord","style":"divine"},{"kind":"text","text":" will fulfill his purpose for me. "},{"kind":"crossref","label":"Ps 57:2","book":"Psa","chapter":57,"verse":2,"letter":"a"},{"kind":"crossref","label":"Php 1:6","book":"Php","chapter":1,"verse":6,"letter":"b"}],"crossRefs":[{"label":"Ps 57:2","book":"Psa","chapter":57,"verse":2},{"label":"Php 1:6","book":"Php","chapter":1,"verse":6}],"footnotes":[]}]},"cachedAt":1783099399719}