{"key":"a556c5305ee15c3f-01|Psa|27","bibleId":"a556c5305ee15c3f-01","bookAbbr":"Psa","chapter":27,"textRevision":"api-bible-csb-2024","parserRevision":"v10","verses":[{"verseId":"a556c5305ee15c3f-01:Psa:27:1","bibleId":"a556c5305ee15c3f-01","bookAbbr":"Psa","bookOrder":18,"chapter":27,"verse":1,"text":"The Lord is my light and my salvation —","textRevision":"api-bible-csb-2024"},{"verseId":"a556c5305ee15c3f-01:Psa:27:2","bibleId":"a556c5305ee15c3f-01","bookAbbr":"Psa","bookOrder":18,"chapter":27,"verse":2,"text":"When evildoers came against me to devour my flesh,","textRevision":"api-bible-csb-2024"},{"verseId":"a556c5305ee15c3f-01:Psa:27:3","bibleId":"a556c5305ee15c3f-01","bookAbbr":"Psa","bookOrder":18,"chapter":27,"verse":3,"text":"Though an army deploys against me,","textRevision":"api-bible-csb-2024"},{"verseId":"a556c5305ee15c3f-01:Psa:27:4","bibleId":"a556c5305ee15c3f-01","bookAbbr":"Psa","bookOrder":18,"chapter":27,"verse":4,"text":"I have asked one thing from the Lord;","textRevision":"api-bible-csb-2024"},{"verseId":"a556c5305ee15c3f-01:Psa:27:5","bibleId":"a556c5305ee15c3f-01","bookAbbr":"Psa","bookOrder":18,"chapter":27,"verse":5,"text":"For he will conceal me in his shelter","textRevision":"api-bible-csb-2024"},{"verseId":"a556c5305ee15c3f-01:Psa:27:6","bibleId":"a556c5305ee15c3f-01","bookAbbr":"Psa","bookOrder":18,"chapter":27,"verse":6,"text":"Then my head will be high","textRevision":"api-bible-csb-2024"},{"verseId":"a556c5305ee15c3f-01:Psa:27:7","bibleId":"a556c5305ee15c3f-01","bookAbbr":"Psa","bookOrder":18,"chapter":27,"verse":7,"text":"Lord, hear my voice when I call;","textRevision":"api-bible-csb-2024"},{"verseId":"a556c5305ee15c3f-01:Psa:27:8","bibleId":"a556c5305ee15c3f-01","bookAbbr":"Psa","bookOrder":18,"chapter":27,"verse":8,"text":"My heart says this about you:","textRevision":"api-bible-csb-2024"},{"verseId":"a556c5305ee15c3f-01:Psa:27:9","bibleId":"a556c5305ee15c3f-01","bookAbbr":"Psa","bookOrder":18,"chapter":27,"verse":9,"text":"Do not hide your face from me;","textRevision":"api-bible-csb-2024"},{"verseId":"a556c5305ee15c3f-01:Psa:27:10","bibleId":"a556c5305ee15c3f-01","bookAbbr":"Psa","bookOrder":18,"chapter":27,"verse":10,"text":"Even if my father and mother abandon me,","textRevision":"api-bible-csb-2024"},{"verseId":"a556c5305ee15c3f-01:Psa:27:11","bibleId":"a556c5305ee15c3f-01","bookAbbr":"Psa","bookOrder":18,"chapter":27,"verse":11,"text":"Because of my adversaries,","textRevision":"api-bible-csb-2024"},{"verseId":"a556c5305ee15c3f-01:Psa:27:12","bibleId":"a556c5305ee15c3f-01","bookAbbr":"Psa","bookOrder":18,"chapter":27,"verse":12,"text":"Do not give me over to the will of my foes,","textRevision":"api-bible-csb-2024"},{"verseId":"a556c5305ee15c3f-01:Psa:27:13","bibleId":"a556c5305ee15c3f-01","bookAbbr":"Psa","bookOrder":18,"chapter":27,"verse":13,"text":"I am certain that I will see the Lord’s goodness","textRevision":"api-bible-csb-2024"},{"verseId":"a556c5305ee15c3f-01:Psa:27:14","bibleId":"a556c5305ee15c3f-01","bookAbbr":"Psa","bookOrder":18,"chapter":27,"verse":14,"text":"Wait for the Lord;","textRevision":"api-bible-csb-2024"}],"layout":{"bibleId":"a556c5305ee15c3f-01","bookAbbr":"Psa","chapter":27,"paragraphStarts":[1,2,3,4,5,6,7,8,9,10,11,12,13,14],"headings":[{"beforeVerse":1,"text":"Of David."}],"poetryBlocks":[{"beforeVerse":1,"level":1},{"beforeVerse":2,"level":1},{"beforeVerse":3,"level":1},{"beforeVerse":4,"level":1},{"beforeVerse":5,"level":1},{"beforeVerse":6,"level":1},{"beforeVerse":7,"level":1},{"beforeVerse":8,"level":1},{"beforeVerse":9,"level":1},{"beforeVerse":10,"level":1},{"beforeVerse":11,"level":1},{"beforeVerse":12,"level":1},{"beforeVerse":13,"level":1},{"beforeVerse":14,"level":1}],"studyByVerse":[{"verseId":"a556c5305ee15c3f-01:Psa:27:1","parts":[{"kind":"text","text":"The "},{"kind":"text","text":"Lord","style":"divine"},{"kind":"text","text":" is my light and my salvation —"}],"crossRefs":[],"footnotes":[]},{"verseId":"a556c5305ee15c3f-01:Psa:27:2","parts":[{"kind":"text","text":"When evildoers came against me to devour my flesh, "},{"kind":"crossref","label":"Ps 14:4","book":"Psa","chapter":14,"verse":4,"letter":"a"}],"crossRefs":[{"label":"Ps 14:4","book":"Psa","chapter":14,"verse":4}],"footnotes":[]},{"verseId":"a556c5305ee15c3f-01:Psa:27:3","parts":[{"kind":"text","text":"Though an army deploys against me,"}],"crossRefs":[],"footnotes":[]},{"verseId":"a556c5305ee15c3f-01:Psa:27:4","parts":[{"kind":"text","text":"I have asked one thing from the "},{"kind":"text","text":"Lord","style":"divine"},{"kind":"text","text":";"}],"crossRefs":[],"footnotes":[]},{"verseId":"a556c5305ee15c3f-01:Psa:27:5","parts":[{"kind":"text","text":"For he will conceal me in his shelter"}],"crossRefs":[],"footnotes":[]},{"verseId":"a556c5305ee15c3f-01:Psa:27:6","parts":[{"kind":"text","text":"Then my head will be high"}],"crossRefs":[],"footnotes":[]},{"verseId":"a556c5305ee15c3f-01:Psa:27:7","parts":[{"kind":"text","text":"Lord","style":"divine"},{"kind":"text","text":", hear my voice when I call;"}],"crossRefs":[],"footnotes":[]},{"verseId":"a556c5305ee15c3f-01:Psa:27:8","parts":[{"kind":"text","text":"My heart says this about you:"}],"crossRefs":[],"footnotes":[]},{"verseId":"a556c5305ee15c3f-01:Psa:27:9","parts":[{"kind":"text","text":"Do not hide your face from me; "},{"kind":"crossref","label":"Ps 69:17","book":"Psa","chapter":69,"verse":17,"letter":"a"},{"kind":"crossref","label":"Ps 102:2","book":"Psa","chapter":102,"verse":2,"letter":"b"},{"kind":"crossref","label":"Ps 143:7","book":"Psa","chapter":143,"verse":7,"letter":"c"}],"crossRefs":[{"label":"Ps 69:17","book":"Psa","chapter":69,"verse":17},{"label":"Ps 102:2","book":"Psa","chapter":102,"verse":2},{"label":"Ps 143:7","book":"Psa","chapter":143,"verse":7}],"footnotes":[]},{"verseId":"a556c5305ee15c3f-01:Psa:27:10","parts":[{"kind":"text","text":"Even if my father and mother abandon me,"}],"crossRefs":[],"footnotes":[]},{"verseId":"a556c5305ee15c3f-01:Psa:27:11","parts":[{"kind":"text","text":"Because of my adversaries,"}],"crossRefs":[],"footnotes":[]},{"verseId":"a556c5305ee15c3f-01:Psa:27:12","parts":[{"kind":"text","text":"Do not give me over to the will of my foes,"}],"crossRefs":[],"footnotes":[]},{"verseId":"a556c5305ee15c3f-01:Psa:27:13","parts":[{"kind":"text","text":"I am certain that I will see the "},{"kind":"text","text":"Lord","style":"divine"},{"kind":"text","text":"’s goodness"}],"crossRefs":[],"footnotes":[]},{"verseId":"a556c5305ee15c3f-01:Psa:27:14","parts":[{"kind":"text","text":"Wait for the "},{"kind":"text","text":"Lord","style":"divine"},{"kind":"text","text":";"}],"crossRefs":[],"footnotes":[]}]},"cachedAt":1783099367391}