{"key":"a556c5305ee15c3f-01|Mic|1","bibleId":"a556c5305ee15c3f-01","bookAbbr":"Mic","chapter":1,"textRevision":"api-bible-csb-2024","parserRevision":"v10","verses":[{"verseId":"a556c5305ee15c3f-01:Mic:1:1","bibleId":"a556c5305ee15c3f-01","bookAbbr":"Mic","bookOrder":32,"chapter":1,"verse":1,"text":"The word of the Lord that came to Micah the Moreshite —what he saw regarding Samaria and Jerusalem in the days of Jotham, Ahaz, and Hezekiah, kings of Judah.","textRevision":"api-bible-csb-2024"},{"verseId":"a556c5305ee15c3f-01:Mic:1:2","bibleId":"a556c5305ee15c3f-01","bookAbbr":"Mic","bookOrder":32,"chapter":1,"verse":2,"text":"Listen, all you peoples;","textRevision":"api-bible-csb-2024"},{"verseId":"a556c5305ee15c3f-01:Mic:1:3","bibleId":"a556c5305ee15c3f-01","bookAbbr":"Mic","bookOrder":32,"chapter":1,"verse":3,"text":"Look, the Lord is leaving his place","textRevision":"api-bible-csb-2024"},{"verseId":"a556c5305ee15c3f-01:Mic:1:4","bibleId":"a556c5305ee15c3f-01","bookAbbr":"Mic","bookOrder":32,"chapter":1,"verse":4,"text":"The mountains will melt beneath him,","textRevision":"api-bible-csb-2024"},{"verseId":"a556c5305ee15c3f-01:Mic:1:5","bibleId":"a556c5305ee15c3f-01","bookAbbr":"Mic","bookOrder":32,"chapter":1,"verse":5,"text":"All this will happen because of Jacob’s rebellion","textRevision":"api-bible-csb-2024"},{"verseId":"a556c5305ee15c3f-01:Mic:1:6","bibleId":"a556c5305ee15c3f-01","bookAbbr":"Mic","bookOrder":32,"chapter":1,"verse":6,"text":"Therefore, I will make Samaria","textRevision":"api-bible-csb-2024"},{"verseId":"a556c5305ee15c3f-01:Mic:1:7","bibleId":"a556c5305ee15c3f-01","bookAbbr":"Mic","bookOrder":32,"chapter":1,"verse":7,"text":"All her carved images will be smashed to pieces;","textRevision":"api-bible-csb-2024"},{"verseId":"a556c5305ee15c3f-01:Mic:1:8","bibleId":"a556c5305ee15c3f-01","bookAbbr":"Mic","bookOrder":32,"chapter":1,"verse":8,"text":"Because of this I will lament and wail;","textRevision":"api-bible-csb-2024"},{"verseId":"a556c5305ee15c3f-01:Mic:1:9","bibleId":"a556c5305ee15c3f-01","bookAbbr":"Mic","bookOrder":32,"chapter":1,"verse":9,"text":"For her wound is incurable","textRevision":"api-bible-csb-2024"},{"verseId":"a556c5305ee15c3f-01:Mic:1:10","bibleId":"a556c5305ee15c3f-01","bookAbbr":"Mic","bookOrder":32,"chapter":1,"verse":10,"text":"Don’t announce it in Gath,","textRevision":"api-bible-csb-2024"},{"verseId":"a556c5305ee15c3f-01:Mic:1:11","bibleId":"a556c5305ee15c3f-01","bookAbbr":"Mic","bookOrder":32,"chapter":1,"verse":11,"text":"Depart in shameful nakedness,","textRevision":"api-bible-csb-2024"},{"verseId":"a556c5305ee15c3f-01:Mic:1:12","bibleId":"a556c5305ee15c3f-01","bookAbbr":"Mic","bookOrder":32,"chapter":1,"verse":12,"text":"Though the residents of Maroth","textRevision":"api-bible-csb-2024"},{"verseId":"a556c5305ee15c3f-01:Mic:1:13","bibleId":"a556c5305ee15c3f-01","bookAbbr":"Mic","bookOrder":32,"chapter":1,"verse":13,"text":"Harness the horses to the chariot,","textRevision":"api-bible-csb-2024"},{"verseId":"a556c5305ee15c3f-01:Mic:1:14","bibleId":"a556c5305ee15c3f-01","bookAbbr":"Mic","bookOrder":32,"chapter":1,"verse":14,"text":"Therefore, send farewell gifts to Moresheth-gath;","textRevision":"api-bible-csb-2024"},{"verseId":"a556c5305ee15c3f-01:Mic:1:15","bibleId":"a556c5305ee15c3f-01","bookAbbr":"Mic","bookOrder":32,"chapter":1,"verse":15,"text":"I will again bring a conqueror","textRevision":"api-bible-csb-2024"},{"verseId":"a556c5305ee15c3f-01:Mic:1:16","bibleId":"a556c5305ee15c3f-01","bookAbbr":"Mic","bookOrder":32,"chapter":1,"verse":16,"text":"Shave yourselves bald and cut off your hair","textRevision":"api-bible-csb-2024"}],"layout":{"bibleId":"a556c5305ee15c3f-01","bookAbbr":"Mic","chapter":1,"paragraphStarts":[1,2,3,4,5,6,7,8,9,10,11,12,13,14,15,16],"headings":[{"beforeVerse":2,"text":"Coming Judgment on Israel"},{"beforeVerse":8,"text":"Micah’s Lament"}],"poetryBlocks":[{"beforeVerse":2,"level":1},{"beforeVerse":3,"level":1},{"beforeVerse":4,"level":1},{"beforeVerse":5,"level":1},{"beforeVerse":6,"level":1},{"beforeVerse":7,"level":1},{"beforeVerse":8,"level":1},{"beforeVerse":9,"level":1},{"beforeVerse":10,"level":1},{"beforeVerse":11,"level":1},{"beforeVerse":12,"level":1},{"beforeVerse":13,"level":1},{"beforeVerse":14,"level":1},{"beforeVerse":15,"level":1},{"beforeVerse":16,"level":1}],"studyByVerse":[{"verseId":"a556c5305ee15c3f-01:Mic:1:1","parts":[{"kind":"text","text":"The word of the "},{"kind":"text","text":"Lord","style":"divine"},{"kind":"text","text":" that came "},{"kind":"crossref","label":"Hs 1:1","book":"Hos","chapter":1,"verse":1,"letter":"a"},{"kind":"crossref","label":"Jl 1:1","book":"Jol","chapter":1,"verse":1,"letter":"b"},{"kind":"crossref","label":"Zp 1:1","book":"Zep","chapter":1,"verse":1,"letter":"c"},{"kind":"text","text":" to Micah "},{"kind":"crossref","label":"2Ch 29:5–11","book":"2Ch","chapter":29,"verse":5,"letter":"d"},{"kind":"crossref","label":"2Ch 32:24–26","book":"2Ch","chapter":32,"verse":24,"letter":"e"},{"kind":"crossref","label":"Jr 26:18","book":"Jer","chapter":26,"verse":18,"letter":"f"},{"kind":"text","text":" the Moreshite "},{"kind":"crossref","label":"Mc 1:14","book":"Mic","chapter":1,"verse":14,"letter":"g"},{"kind":"text","text":" —what he saw regarding Samaria and Jerusalem in the days of Jotham, "},{"kind":"crossref","label":"2Kg 15:5","book":"2Ki","chapter":15,"verse":5,"letter":"h"},{"kind":"crossref","label":"2Kg 15:32","book":"2Ki","chapter":15,"verse":32,"letter":"i"},{"kind":"crossref","label":"2Ch 27:1–9","book":"2Ch","chapter":27,"verse":1,"letter":"j"},{"kind":"crossref","label":"Is 1:1","book":"Isa","chapter":1,"verse":1,"letter":"k"},{"kind":"crossref","label":"Hs 1:1","book":"Hos","chapter":1,"verse":1,"letter":"l"},{"kind":"text","text":" Ahaz, "},{"kind":"crossref","label":"2Kg 16:1","book":"2Ki","chapter":16,"verse":1,"letter":"m"},{"kind":"crossref","label":"2Ch 28:1–27","book":"2Ch","chapter":28,"verse":1,"letter":"n"},{"kind":"crossref","label":"Is 7:1–12","book":"Isa","chapter":7,"verse":1,"letter":"o"},{"kind":"text","text":" and Hezekiah, "},{"kind":"crossref","label":"2Kg 18:1","book":"2Ki","chapter":18,"verse":1,"letter":"p"},{"kind":"crossref","label":"2Ch 29:1–31","book":"2Ch","chapter":29,"verse":1,"letter":"q"},{"kind":"text","text":" kings of Judah."}],"crossRefs":[{"label":"Hs 1:1","book":"Hos","chapter":1,"verse":1},{"label":"Jl 1:1","book":"Jol","chapter":1,"verse":1},{"label":"Zp 1:1","book":"Zep","chapter":1,"verse":1},{"label":"2Ch 29:5–11","book":"2Ch","chapter":29,"verse":5},{"label":"2Ch 32:24–26","book":"2Ch","chapter":32,"verse":24},{"label":"Jr 26:18","book":"Jer","chapter":26,"verse":18},{"label":"Mc 1:14","book":"Mic","chapter":1,"verse":14},{"label":"2Kg 15:5","book":"2Ki","chapter":15,"verse":5},{"label":"2Kg 15:32","book":"2Ki","chapter":15,"verse":32},{"label":"2Ch 27:1–9","book":"2Ch","chapter":27,"verse":1},{"label":"Is 1:1","book":"Isa","chapter":1,"verse":1},{"label":"Hs 1:1","book":"Hos","chapter":1,"verse":1},{"label":"2Kg 16:1","book":"2Ki","chapter":16,"verse":1},{"label":"2Ch 28:1–27","book":"2Ch","chapter":28,"verse":1},{"label":"Is 7:1–12","book":"Isa","chapter":7,"verse":1},{"label":"2Kg 18:1","book":"2Ki","chapter":18,"verse":1},{"label":"2Ch 29:1–31","book":"2Ch","chapter":29,"verse":1}],"footnotes":[]},{"verseId":"a556c5305ee15c3f-01:Mic:1:2","parts":[{"kind":"text","text":"Listen, all you peoples; "},{"kind":"crossref","label":"1Kg 22:28","book":"1Ki","chapter":22,"verse":28,"letter":"a"},{"kind":"crossref","label":"2Ch 18:27","book":"2Ch","chapter":18,"verse":27,"letter":"b"},{"kind":"crossref","label":"Jr 6:19","book":"Jer","chapter":6,"verse":19,"letter":"c"},{"kind":"crossref","label":"Jr 22:29","book":"Jer","chapter":22,"verse":29,"letter":"d"}],"crossRefs":[{"label":"1Kg 22:28","book":"1Ki","chapter":22,"verse":28},{"label":"2Ch 18:27","book":"2Ch","chapter":18,"verse":27},{"label":"Jr 6:19","book":"Jer","chapter":6,"verse":19},{"label":"Jr 22:29","book":"Jer","chapter":22,"verse":29}],"footnotes":[]},{"verseId":"a556c5305ee15c3f-01:Mic:1:3","parts":[{"kind":"text","text":"Look, the "},{"kind":"text","text":"Lord","style":"divine"},{"kind":"text","text":" is leaving his place "},{"kind":"crossref","label":"Is 26:21","book":"Isa","chapter":26,"verse":21,"letter":"a"}],"crossRefs":[{"label":"Is 26:21","book":"Isa","chapter":26,"verse":21}],"footnotes":[]},{"verseId":"a556c5305ee15c3f-01:Mic:1:4","parts":[{"kind":"text","text":"The mountains will melt beneath him,"}],"crossRefs":[],"footnotes":[]},{"verseId":"a556c5305ee15c3f-01:Mic:1:5","parts":[{"kind":"text","text":"All this will happen because of Jacob’s rebellion"}],"crossRefs":[],"footnotes":[]},{"verseId":"a556c5305ee15c3f-01:Mic:1:6","parts":[{"kind":"text","text":"Therefore, I will make Samaria"}],"crossRefs":[],"footnotes":[]},{"verseId":"a556c5305ee15c3f-01:Mic:1:7","parts":[{"kind":"text","text":"All her carved images will be smashed "},{"kind":"crossref","label":"Dt 9:21","book":"Deu","chapter":9,"verse":21,"letter":"a"},{"kind":"crossref","label":"2Ch 34:7","book":"2Ch","chapter":34,"verse":7,"letter":"b"},{"kind":"text","text":" to pieces;"}],"crossRefs":[{"label":"Dt 9:21","book":"Deu","chapter":9,"verse":21},{"label":"2Ch 34:7","book":"2Ch","chapter":34,"verse":7}],"footnotes":[]},{"verseId":"a556c5305ee15c3f-01:Mic:1:8","parts":[{"kind":"text","text":"Because of this I will lament and wail;"}],"crossRefs":[],"footnotes":[]},{"verseId":"a556c5305ee15c3f-01:Mic:1:9","parts":[{"kind":"text","text":"For her wound is incurable "},{"kind":"crossref","label":"Is 3:26","book":"Isa","chapter":3,"verse":26,"letter":"a"},{"kind":"crossref","label":"Jr 30:12","book":"Jer","chapter":30,"verse":12,"letter":"b"},{"kind":"crossref","label":"Jr 30:15","book":"Jer","chapter":30,"verse":15,"letter":"c"}],"crossRefs":[{"label":"Is 3:26","book":"Isa","chapter":3,"verse":26},{"label":"Jr 30:12","book":"Jer","chapter":30,"verse":12},{"label":"Jr 30:15","book":"Jer","chapter":30,"verse":15}],"footnotes":[]},{"verseId":"a556c5305ee15c3f-01:Mic:1:10","parts":[{"kind":"text","text":"Don’t announce it in Gath, "},{"kind":"crossref","label":"2Sm 1:20","book":"2Sa","chapter":1,"verse":20,"letter":"a"}],"crossRefs":[{"label":"2Sm 1:20","book":"2Sa","chapter":1,"verse":20}],"footnotes":[]},{"verseId":"a556c5305ee15c3f-01:Mic:1:11","parts":[{"kind":"text","text":"Depart in shameful nakedness, "},{"kind":"crossref","label":"Ezk 23:29","book":"Ezk","chapter":23,"verse":29,"letter":"a"}],"crossRefs":[{"label":"Ezk 23:29","book":"Ezk","chapter":23,"verse":29}],"footnotes":[]},{"verseId":"a556c5305ee15c3f-01:Mic:1:12","parts":[{"kind":"text","text":"Though the residents of Maroth"}],"crossRefs":[],"footnotes":[]},{"verseId":"a556c5305ee15c3f-01:Mic:1:13","parts":[{"kind":"text","text":"Harness the horses to the chariot,"}],"crossRefs":[],"footnotes":[]},{"verseId":"a556c5305ee15c3f-01:Mic:1:14","parts":[{"kind":"text","text":"Therefore, send farewell gifts "},{"kind":"crossref","label":"2Kg 16:8","book":"2Ki","chapter":16,"verse":8,"letter":"a"},{"kind":"text","text":" to Moresheth-gath;"}],"crossRefs":[{"label":"2Kg 16:8","book":"2Ki","chapter":16,"verse":8}],"footnotes":[]},{"verseId":"a556c5305ee15c3f-01:Mic:1:15","parts":[{"kind":"text","text":"I will again bring a conqueror"}],"crossRefs":[],"footnotes":[]},{"verseId":"a556c5305ee15c3f-01:Mic:1:16","parts":[{"kind":"text","text":"Shave yourselves bald and cut off your hair "},{"kind":"crossref","label":"Jb 1:20","book":"Job","chapter":1,"verse":20,"letter":"a"},{"kind":"crossref","label":"Is 22:12","book":"Isa","chapter":22,"verse":12,"letter":"b"},{"kind":"crossref","label":"Jr 7:29","book":"Jer","chapter":7,"verse":29,"letter":"c"}],"crossRefs":[{"label":"Jb 1:20","book":"Job","chapter":1,"verse":20},{"label":"Is 22:12","book":"Isa","chapter":22,"verse":12},{"label":"Jr 7:29","book":"Jer","chapter":7,"verse":29}],"footnotes":[]}]},"cachedAt":1783099484151}